xin_mcp_demo/__init__.py
xin_mcp_demo-0.1.0.dist-info/WHEEL
xin_mcp_demo-0.1.0.dist-info/entry_points.txt
xin_mcp_demo-0.1.0.dist-info/METADATA
xin_mcp_demo-0.1.0.dist-info/RECORD
