Metadata-Version: 2.3
Name: xin-mcp-demo
Version: 0.1.0
Summary: Add your description here
Author: root
Author-email: root <itheima@itcast.cn>
Requires-Dist: mcp[cli]>=1.13.1
Requires-Python: >=3.13
